photo_organizer/__init__.py
photo_organizer/main.py
photo_organizer-2.0.0.dist-info/licenses/LICENSE
tests/__init__.py
tests/test_get_creation_date.py
tests/test_list_files.py
tests/test_main.py
tests/test_organize_files.py
photo_organizer-2.0.0.dist-info/METADATA
photo_organizer-2.0.0.dist-info/WHEEL
photo_organizer-2.0.0.dist-info/entry_points.txt
photo_organizer-2.0.0.dist-info/top_level.txt
photo_organizer-2.0.0.dist-info/RECORD
