Metadata-Version: 2.4
Name: photo_organizer
Version: 2.0.0
Summary: A script to organize photos by creation date into year/month/day folders.
Home-page: https://github.com/Supporterino/photo-organizer
Author: Supporterino
Author-email: Supporterino <lars@roth-kl.de>
License: MIT
Project-URL: Homepage, https://github.com/Supporterino/photo-organizer
Requires-Python: >=3.10
License-File: LICENSE
Requires-Dist: tqdm
Requires-Dist: exifread
Dynamic: author
Dynamic: home-page
Dynamic: license-file
Dynamic: requires-python
